{"trial_id": "0076", "hyperparameters": {"space": [{"class_name": "Choice", "config": {"name": "activation", "default": "relu", "conditions": [], "values": ["relu", "tanh", "sigmoid"], "ordered": false}}, {"class_name": "Int", "config": {"name": "first_units", "default": null, "conditions": [], "min_value": 1, "max_value": 10, "step": 2, "sampling": "linear"}}, {"class_name": "Int", "config": {"name": "num_layers", "default": null, "conditions": [], "min_value": 1, "max_value": 6, "step": 1, "sampling": "linear"}}, {"class_name": "Int", "config": {"name": "units_0", "default": null, "conditions": [], "min_value": 1, "max_value": 10, "step": 2, "sampling": "linear"}}, {"class_name": "Int", "config": {"name": "units_1", "default": null, "conditions": [], "min_value": 1, "max_value": 10, "step": 2, "sampling": "linear"}}, {"class_name": "Int", "config": {"name": "units_2", "default": null, "conditions": [], "min_value": 1, "max_value": 10, "step": 2, "sampling": "linear"}}, {"class_name": "Int", "config": {"name": "units_3", "default": null, "conditions": [], "min_value": 1, "max_value": 10, "step": 2, "sampling": "linear"}}, {"class_name": "Int", "config": {"name": "units_4", "default": null, "conditions": [], "min_value": 1, "max_value": 10, "step": 2, "sampling": "linear"}}, {"class_name": "Int", "config": {"name": "units_5", "default": null, "conditions": [], "min_value": 1, "max_value": 10, "step": 2, "sampling": "linear"}}], "values": {"activation": "tanh", "first_units": 7, "num_layers": 2, "units_0": 5, "units_1": 7, "units_2": 5, "units_3": 3, "units_4": 1, "units_5": 1, "tuner/epochs": 17, "tuner/initial_epoch": 0, "tuner/bracket": 1, "tuner/round": 0}}, "metrics": {"metrics": {"accuracy": {"direction": "max", "observations": [{"value": [0.7320012450218201], "step": 12}]}, "loss": {"direction": "min", "observations": [{"value": [0.5505658984184265], "step": 12}]}, "val_accuracy": {"direction": "max", "observations": [{"value": [0.7325947284698486], "step": 12}]}, "val_loss": {"direction": "min", "observations": [{"value": [0.554336667060852], "step": 12}]}}}, "score": 0.7325947284698486, "best_step": 12, "status": "COMPLETED", "message": null}